wareflow_analysis/__init__.py
wareflow_analysis/cli.py
wareflow_analysis/init.py
wareflow_analysis/py.typed
wareflow_analysis/analyze/__init__.py
wareflow_analysis/analyze/abc.py
wareflow_analysis/analyze/inventory.py
wareflow_analysis/data_import/__init__.py
wareflow_analysis/data_import/autopilot.py
wareflow_analysis/data_import/config_refiner.py
wareflow_analysis/data_import/header_detector.py
wareflow_analysis/data_import/importer.py
wareflow_analysis/database/__init__.py
wareflow_analysis/database/manager.py
wareflow_analysis/export/__init__.py
wareflow_analysis/export/excel_builder.py
wareflow_analysis/export/formatters.py
wareflow_analysis/export/reports/__init__.py
wareflow_analysis/export/reports/abc_report.py
wareflow_analysis/export/reports/inventory_report.py
wareflow_analysis/templates/README.md
wareflow_analysis/templates/analyze.py
wareflow_analysis/templates/config.yaml
wareflow_analysis/templates/export.py
wareflow_analysis/templates/import.py
wareflow_analysis/templates/schema.sql
wareflow_analysis/validation/__init__.py
wareflow_analysis/validation/models.py
wareflow_analysis/validation/reporters.py
wareflow_analysis/validation/schema_parser.py
wareflow_analysis/validation/validator.py
wareflow_analysis/validation/auto_fix/__init__.py
wareflow_analysis/validation/checks/__init__.py
wareflow_analysis/validation/checks/column_checks.py
wareflow_analysis/validation/checks/file_checks.py
wareflow_analysis/validation/checks/null_checks.py
wareflow_analysis/validation/checks/pk_checks.py
wareflow_analysis/validation/checks/sheet_checks.py
wareflow_analysis/validation/checks/type_checks.py
wareflow_analysis-0.6.0.dist-info/METADATA
wareflow_analysis-0.6.0.dist-info/WHEEL
wareflow_analysis-0.6.0.dist-info/entry_points.txt
wareflow_analysis-0.6.0.dist-info/RECORD
