Metadata-Version: 2.4
Name: wareflow-analysis
Version: 0.6.0
Summary: Warehouse data analysis CLI tool
Project-URL: Homepage, https://github.com/wareflowx/wareflow-analysis
Project-URL: Repository, https://github.com/wareflowx/wareflow-analysis
Project-URL: Issues, https://github.com/wareflowx/wareflow-analysis/issues
Author-email: Code with dave <davidddpereiraaa6@gmail.com>
Classifier: License :: OSI Approved :: MIT License
Classifier: Operating System :: OS Independent
Classifier: Programming Language :: Python :: 3
Requires-Python: >=3.10
Requires-Dist: excel-to-sql>=0.4.0
Requires-Dist: openpyxl>=3.0
Requires-Dist: pandas>=2.0
Requires-Dist: pyyaml
Requires-Dist: typer>=0.21
